[
  {
    "ContainingType": "HaulEaseNetcore.Controllers.CargoController",
    "Method": "GetCargos",
    "RelativePath": "api/Cargo",
    "HttpMethod": "GET",
    "IsController": true,
    "Order": 0,
    "Parameters": [],
    "ReturnTypes": [
      {
        "Type": "System.Collections.Generic.IEnumerable\u00601[[HaulEaseNetcore.Models.Cargo, HaulEaseNetcore, Version=1.0.0.0, Culture=neutral, PublicKeyToken=null]]",
        "MediaTypes": [
          "text/plain",
          "application/json",
          "text/json"
        ],
        "StatusCode": 200
      }
    ]
  },
  {
    "ContainingType": "HaulEaseNetcore.Controllers.CargoController",
    "Method": "PostCargo",
    "RelativePath": "api/Cargo",
    "HttpMethod": "POST",
    "IsController": true,
    "Order": 0,
    "Parameters": [
      {
        "Name": "_cargo",
        "Type": "HaulEaseNetcore.Models.Cargo",
        "IsRequired": true
      }
    ],
    "ReturnTypes": [
      {
        "Type": "HaulEaseNetcore.Models.Cargo",
        "MediaTypes": [
          "text/plain",
          "application/json",
          "text/json"
        ],
        "StatusCode": 200
      }
    ]
  },
  {
    "ContainingType": "HaulEaseNetcore.Controllers.CargoController",
    "Method": "GetCargo",
    "RelativePath": "api/Cargo/{id}",
    "HttpMethod": "GET",
    "IsController": true,
    "Order": 0,
    "Parameters": [
      {
        "Name": "id",
        "Type": "System.Int32",
        "IsRequired": true
      }
    ],
    "ReturnTypes": [
      {
        "Type": "HaulEaseNetcore.Models.Cargo",
        "MediaTypes": [
          "text/plain",
          "application/json",
          "text/json"
        ],
        "StatusCode": 200
      }
    ]
  },
  {
    "ContainingType": "HaulEaseNetcore.Controllers.CargoController",
    "Method": "PutCargo",
    "RelativePath": "api/Cargo/{id}",
    "HttpMethod": "PUT",
    "IsController": true,
    "Order": 0,
    "Parameters": [
      {
        "Name": "id",
        "Type": "System.Int32",
        "IsRequired": true
      },
      {
        "Name": "_cargo",
        "Type": "HaulEaseNetcore.Models.Cargo",
        "IsRequired": true
      }
    ],
    "ReturnTypes": []
  },
  {
    "ContainingType": "HaulEaseNetcore.Controllers.CargoController",
    "Method": "DeleteCargo",
    "RelativePath": "api/Cargo/{id}",
    "HttpMethod": "DELETE",
    "IsController": true,
    "Order": 0,
    "Parameters": [
      {
        "Name": "id",
        "Type": "System.Int32",
        "IsRequired": true
      }
    ],
    "ReturnTypes": []
  },
  {
    "ContainingType": "HaulEaseNetcore.Controllers.ConsignorController",
    "Method": "GetConsignors",
    "RelativePath": "api/Consignor",
    "HttpMethod": "GET",
    "IsController": true,
    "Order": 0,
    "Parameters": [],
    "ReturnTypes": [
      {
        "Type": "System.Collections.Generic.IEnumerable\u00601[[HaulEaseNetcore.Models.Consignor, HaulEaseNetcore, Version=1.0.0.0, Culture=neutral, PublicKeyToken=null]]",
        "MediaTypes": [
          "text/plain",
          "application/json",
          "text/json"
        ],
        "StatusCode": 200
      }
    ]
  },
  {
    "ContainingType": "HaulEaseNetcore.Controllers.ConsignorController",
    "Method": "PostConsignor",
    "RelativePath": "api/Consignor",
    "HttpMethod": "POST",
    "IsController": true,
    "Order": 0,
    "Parameters": [
      {
        "Name": "_consignor",
        "Type": "HaulEaseNetcore.Models.Consignor",
        "IsRequired": true
      }
    ],
    "ReturnTypes": [
      {
        "Type": "HaulEaseNetcore.Models.Consignor",
        "MediaTypes": [
          "text/plain",
          "application/json",
          "text/json"
        ],
        "StatusCode": 200
      }
    ]
  },
  {
    "ContainingType": "HaulEaseNetcore.Controllers.ConsignorController",
    "Method": "GetConsignor",
    "RelativePath": "api/Consignor/{id}",
    "HttpMethod": "GET",
    "IsController": true,
    "Order": 0,
    "Parameters": [
      {
        "Name": "id",
        "Type": "System.Int32",
        "IsRequired": true
      }
    ],
    "ReturnTypes": [
      {
        "Type": "HaulEaseNetcore.Models.Consignor",
        "MediaTypes": [
          "text/plain",
          "application/json",
          "text/json"
        ],
        "StatusCode": 200
      }
    ]
  },
  {
    "ContainingType": "HaulEaseNetcore.Controllers.ConsignorController",
    "Method": "PutConsignor",
    "RelativePath": "api/Consignor/{id}",
    "HttpMethod": "PUT",
    "IsController": true,
    "Order": 0,
    "Parameters": [
      {
        "Name": "id",
        "Type": "System.Int32",
        "IsRequired": true
      },
      {
        "Name": "_consignor",
        "Type": "HaulEaseNetcore.Models.Consignor",
        "IsRequired": true
      }
    ],
    "ReturnTypes": []
  },
  {
    "ContainingType": "HaulEaseNetcore.Controllers.ConsignorController",
    "Method": "DeleteConsignor",
    "RelativePath": "api/Consignor/{id}",
    "HttpMethod": "DELETE",
    "IsController": true,
    "Order": 0,
    "Parameters": [
      {
        "Name": "id",
        "Type": "System.Int32",
        "IsRequired": true
      }
    ],
    "ReturnTypes": []
  },
  {
    "ContainingType": "HaulEaseNetcore.Controllers.ConsignorController",
    "Method": "CheckConsignorEmail",
    "RelativePath": "api/Consignor/email/{email}",
    "HttpMethod": "GET",
    "IsController": true,
    "Order": 0,
    "Parameters": [
      {
        "Name": "email",
        "Type": "System.String",
        "IsRequired": true
      }
    ],
    "ReturnTypes": [
      {
        "Type": "HaulEaseNetcore.Models.Consignor",
        "MediaTypes": [
          "text/plain",
          "application/json",
          "text/json"
        ],
        "StatusCode": 200
      }
    ]
  },
  {
    "ContainingType": "HaulEaseNetcore.Controllers.ConsignorController",
    "Method": "CheckConsignor",
    "RelativePath": "api/Consignor/email/{email}/password/{password}",
    "HttpMethod": "GET",
    "IsController": true,
    "Order": 0,
    "Parameters": [
      {
        "Name": "email",
        "Type": "System.String",
        "IsRequired": true
      },
      {
        "Name": "password",
        "Type": "System.String",
        "IsRequired": true
      }
    ],
    "ReturnTypes": [
      {
        "Type": "HaulEaseNetcore.Models.Consignor",
        "MediaTypes": [
          "text/plain",
          "application/json",
          "text/json"
        ],
        "StatusCode": 200
      }
    ]
  },
  {
    "ContainingType": "HaulEaseNetcore.Controllers.PaymentController",
    "Method": "GetPayments",
    "RelativePath": "api/Payment",
    "HttpMethod": "GET",
    "IsController": true,
    "Order": 0,
    "Parameters": [],
    "ReturnTypes": [
      {
        "Type": "System.Collections.Generic.IEnumerable\u00601[[HaulEaseNetcore.Models.Payment, HaulEaseNetcore, Version=1.0.0.0, Culture=neutral, PublicKeyToken=null]]",
        "MediaTypes": [
          "text/plain",
          "application/json",
          "text/json"
        ],
        "StatusCode": 200
      }
    ]
  },
  {
    "ContainingType": "HaulEaseNetcore.Controllers.PaymentController",
    "Method": "PostPayment",
    "RelativePath": "api/Payment",
    "HttpMethod": "POST",
    "IsController": true,
    "Order": 0,
    "Parameters": [
      {
        "Name": "_payment",
        "Type": "HaulEaseNetcore.Models.Payment",
        "IsRequired": true
      }
    ],
    "ReturnTypes": [
      {
        "Type": "HaulEaseNetcore.Models.Payment",
        "MediaTypes": [
          "text/plain",
          "application/json",
          "text/json"
        ],
        "StatusCode": 200
      }
    ]
  },
  {
    "ContainingType": "HaulEaseNetcore.Controllers.PaymentController",
    "Method": "GetPayment",
    "RelativePath": "api/Payment/{id}",
    "HttpMethod": "GET",
    "IsController": true,
    "Order": 0,
    "Parameters": [
      {
        "Name": "id",
        "Type": "System.Int32",
        "IsRequired": true
      }
    ],
    "ReturnTypes": [
      {
        "Type": "HaulEaseNetcore.Models.Payment",
        "MediaTypes": [
          "text/plain",
          "application/json",
          "text/json"
        ],
        "StatusCode": 200
      }
    ]
  },
  {
    "ContainingType": "HaulEaseNetcore.Controllers.PaymentController",
    "Method": "PutPayment",
    "RelativePath": "api/Payment/{id}",
    "HttpMethod": "PUT",
    "IsController": true,
    "Order": 0,
    "Parameters": [
      {
        "Name": "id",
        "Type": "System.Int32",
        "IsRequired": true
      },
      {
        "Name": "_payment",
        "Type": "HaulEaseNetcore.Models.Payment",
        "IsRequired": true
      }
    ],
    "ReturnTypes": []
  },
  {
    "ContainingType": "HaulEaseNetcore.Controllers.PaymentController",
    "Method": "DeletePayment",
    "RelativePath": "api/Payment/{id}",
    "HttpMethod": "DELETE",
    "IsController": true,
    "Order": 0,
    "Parameters": [
      {
        "Name": "id",
        "Type": "System.Int32",
        "IsRequired": true
      }
    ],
    "ReturnTypes": []
  },
  {
    "ContainingType": "HaulEaseNetcore.Controllers.ShipmentController",
    "Method": "GetShipments",
    "RelativePath": "api/Shipment",
    "HttpMethod": "GET",
    "IsController": true,
    "Order": 0,
    "Parameters": [],
    "ReturnTypes": [
      {
        "Type": "System.Collections.Generic.IEnumerable\u00601[[HaulEaseNetcore.Models.Shipment, HaulEaseNetcore, Version=1.0.0.0, Culture=neutral, PublicKeyToken=null]]",
        "MediaTypes": [
          "text/plain",
          "application/json",
          "text/json"
        ],
        "StatusCode": 200
      }
    ]
  },
  {
    "ContainingType": "HaulEaseNetcore.Controllers.ShipmentController",
    "Method": "PostShipment",
    "RelativePath": "api/Shipment",
    "HttpMethod": "POST",
    "IsController": true,
    "Order": 0,
    "Parameters": [
      {
        "Name": "_shipment",
        "Type": "HaulEaseNetcore.Models.Shipment",
        "IsRequired": true
      }
    ],
    "ReturnTypes": [
      {
        "Type": "HaulEaseNetcore.Models.Shipment",
        "MediaTypes": [
          "text/plain",
          "application/json",
          "text/json"
        ],
        "StatusCode": 200
      }
    ]
  },
  {
    "ContainingType": "HaulEaseNetcore.Controllers.ShipmentController",
    "Method": "GetShipment",
    "RelativePath": "api/Shipment/{id}",
    "HttpMethod": "GET",
    "IsController": true,
    "Order": 0,
    "Parameters": [
      {
        "Name": "id",
        "Type": "System.Int32",
        "IsRequired": true
      }
    ],
    "ReturnTypes": [
      {
        "Type": "HaulEaseNetcore.Models.Shipment",
        "MediaTypes": [
          "text/plain",
          "application/json",
          "text/json"
        ],
        "StatusCode": 200
      }
    ]
  },
  {
    "ContainingType": "HaulEaseNetcore.Controllers.ShipmentController",
    "Method": "PutShipment",
    "RelativePath": "api/Shipment/{id}",
    "HttpMethod": "PUT",
    "IsController": true,
    "Order": 0,
    "Parameters": [
      {
        "Name": "id",
        "Type": "System.Int32",
        "IsRequired": true
      },
      {
        "Name": "_shipment",
        "Type": "HaulEaseNetcore.Models.Shipment",
        "IsRequired": true
      }
    ],
    "ReturnTypes": []
  },
  {
    "ContainingType": "HaulEaseNetcore.Controllers.ShipmentController",
    "Method": "DeleteShipment",
    "RelativePath": "api/Shipment/{id}",
    "HttpMethod": "DELETE",
    "IsController": true,
    "Order": 0,
    "Parameters": [
      {
        "Name": "id",
        "Type": "System.Int32",
        "IsRequired": true
      }
    ],
    "ReturnTypes": []
  },
  {
    "ContainingType": "HaulEaseNetcore.Controllers.TrackingController",
    "Method": "GetTrackings",
    "RelativePath": "api/Tracking",
    "HttpMethod": "GET",
    "IsController": true,
    "Order": 0,
    "Parameters": [],
    "ReturnTypes": [
      {
        "Type": "System.Collections.Generic.IEnumerable\u00601[[HaulEaseNetcore.Models.Tracking, HaulEaseNetcore, Version=1.0.0.0, Culture=neutral, PublicKeyToken=null]]",
        "MediaTypes": [
          "text/plain",
          "application/json",
          "text/json"
        ],
        "StatusCode": 200
      }
    ]
  },
  {
    "ContainingType": "HaulEaseNetcore.Controllers.TrackingController",
    "Method": "PostTracking",
    "RelativePath": "api/Tracking",
    "HttpMethod": "POST",
    "IsController": true,
    "Order": 0,
    "Parameters": [
      {
        "Name": "_tracking",
        "Type": "HaulEaseNetcore.Models.Tracking",
        "IsRequired": true
      }
    ],
    "ReturnTypes": [
      {
        "Type": "HaulEaseNetcore.Models.Tracking",
        "MediaTypes": [
          "text/plain",
          "application/json",
          "text/json"
        ],
        "StatusCode": 200
      }
    ]
  },
  {
    "ContainingType": "HaulEaseNetcore.Controllers.TrackingController",
    "Method": "GetTracking",
    "RelativePath": "api/Tracking/{id}",
    "HttpMethod": "GET",
    "IsController": true,
    "Order": 0,
    "Parameters": [
      {
        "Name": "id",
        "Type": "System.Int32",
        "IsRequired": true
      }
    ],
    "ReturnTypes": [
      {
        "Type": "HaulEaseNetcore.Models.Tracking",
        "MediaTypes": [
          "text/plain",
          "application/json",
          "text/json"
        ],
        "StatusCode": 200
      }
    ]
  },
  {
    "ContainingType": "HaulEaseNetcore.Controllers.TrackingController",
    "Method": "PutTracking",
    "RelativePath": "api/Tracking/{id}",
    "HttpMethod": "PUT",
    "IsController": true,
    "Order": 0,
    "Parameters": [
      {
        "Name": "id",
        "Type": "System.Int32",
        "IsRequired": true
      },
      {
        "Name": "_tracking",
        "Type": "HaulEaseNetcore.Models.Tracking",
        "IsRequired": true
      }
    ],
    "ReturnTypes": []
  },
  {
    "ContainingType": "HaulEaseNetcore.Controllers.TrackingController",
    "Method": "DeleteTracking",
    "RelativePath": "api/Tracking/{id}",
    "HttpMethod": "DELETE",
    "IsController": true,
    "Order": 0,
    "Parameters": [
      {
        "Name": "id",
        "Type": "System.Int32",
        "IsRequired": true
      }
    ],
    "ReturnTypes": []
  },
  {
    "ContainingType": "HaulEaseNetcore.Controllers.TruckController",
    "Method": "GetTrucks",
    "RelativePath": "api/Truck",
    "HttpMethod": "GET",
    "IsController": true,
    "Order": 0,
    "Parameters": [],
    "ReturnTypes": [
      {
        "Type": "System.Collections.Generic.IEnumerable\u00601[[HaulEaseNetcore.Models.Truck, HaulEaseNetcore, Version=1.0.0.0, Culture=neutral, PublicKeyToken=null]]",
        "MediaTypes": [
          "text/plain",
          "application/json",
          "text/json"
        ],
        "StatusCode": 200
      }
    ]
  },
  {
    "ContainingType": "HaulEaseNetcore.Controllers.TruckController",
    "Method": "PostTruck",
    "RelativePath": "api/Truck",
    "HttpMethod": "POST",
    "IsController": true,
    "Order": 0,
    "Parameters": [
      {
        "Name": "_truck",
        "Type": "HaulEaseNetcore.Models.Truck",
        "IsRequired": true
      }
    ],
    "ReturnTypes": [
      {
        "Type": "HaulEaseNetcore.Models.Truck",
        "MediaTypes": [
          "text/plain",
          "application/json",
          "text/json"
        ],
        "StatusCode": 200
      }
    ]
  },
  {
    "ContainingType": "HaulEaseNetcore.Controllers.TruckController",
    "Method": "GetTruck",
    "RelativePath": "api/Truck/{id}",
    "HttpMethod": "GET",
    "IsController": true,
    "Order": 0,
    "Parameters": [
      {
        "Name": "id",
        "Type": "System.Int32",
        "IsRequired": true
      }
    ],
    "ReturnTypes": [
      {
        "Type": "HaulEaseNetcore.Models.Truck",
        "MediaTypes": [
          "text/plain",
          "application/json",
          "text/json"
        ],
        "StatusCode": 200
      }
    ]
  },
  {
    "ContainingType": "HaulEaseNetcore.Controllers.TruckController",
    "Method": "PutTruck",
    "RelativePath": "api/Truck/{id}",
    "HttpMethod": "PUT",
    "IsController": true,
    "Order": 0,
    "Parameters": [
      {
        "Name": "id",
        "Type": "System.Int32",
        "IsRequired": true
      },
      {
        "Name": "_truck",
        "Type": "HaulEaseNetcore.Models.Truck",
        "IsRequired": true
      }
    ],
    "ReturnTypes": []
  },
  {
    "ContainingType": "HaulEaseNetcore.Controllers.TruckController",
    "Method": "DeleteTruck",
    "RelativePath": "api/Truck/{id}",
    "HttpMethod": "DELETE",
    "IsController": true,
    "Order": 0,
    "Parameters": [
      {
        "Name": "id",
        "Type": "System.Int32",
        "IsRequired": true
      }
    ],
    "ReturnTypes": []
  }
]